fasthttppy
