Metadata-Version: 2.1
Name: fasthttppy
Version: 0.0.2
Summary: Python implementation of Golang FastHttp
Home-page: https://github.com/Peticali/FastHttpPy
Author: Pedro Palmeira
Author-email: pedropalmeira68@gmail.com
License: MIT
License-File: LICENSE
